{
  "id": "dragon-ball-gt-opening-dan-dan-kokoro-hikareteku-piano-solo",
  "title": "Dan dan Kokoro Hikareteku",
  "artist": "Dragon Ball Gt",
  "bpm": 120,
  "difficulty": "Hard",
  "duration": 114.0,
  "genre": "anime",
  "notes": [
    {
      "key": "G2,G3",
      "time": 0.0
    },
    {
      "key": "G2,G3",
      "time": 0.25
    },
    {
      "key": "C4,D2,G2,G2,G3",
      "time": 0.5
    },
    {
      "key": "D2,G2,G2",
      "time": 1.0
    },
    {
      "key": "D2,G2,G2",
      "time": 2.0
    },
    {
      "key": "D2,G2,G2",
      "time": 2.5
    },
    {
      "key": "D2,G2,G2",
      "time": 3.0
    },
    {
      "key": "D2,G2,G2",
      "time": 4.0
    },
    {
      "key": "D2,G2,G2",
      "time": 4.5
    },
    {
      "key": "G3,G4",
      "time": 5.0
    },
    {
      "key": "F3,F4",
      "time": 5.5
    },
    {
      "key": "G3,G4",
      "time": 6.0
    },
    {
      "key": "E3,E4",
      "time": 6.5
    },
    {
      "key": "G3,G4",
      "time": 7.0
    },
    {
      "key": "D3,D4",
      "time": 7.5
    },
    {
      "key": "G3,G4",
      "time": 8.0
    },
    {
      "key": "C2,C2,C4,E4,G3,G4",
      "time": 8.5
    },
    {
      "key": "C4,E4,G3,G4",
      "time": 9.5
    },
    {
      "key": "C3,E2,G2",
      "time": 10.0
    },
    {
      "key": "E3,E4",
      "time": 10.5
    },
    {
      "key": "F3,F4",
      "time": 11.0
    },
    {
      "key": "C3,E2,G2,G3,G4",
      "time": 11.5
    },
    {
      "key": "A3,A4",
      "time": 12.0
    },
    {
      "key": "B3,D4,G2,G2,G3,G4",
      "time": 12.5
    },
    {
      "key": "F3,F4",
      "time": 13.5
    },
    {
      "key": "B2,D2,G2",
      "time": 14.0
    },
    {
      "key": "E3,E4",
      "time": 14.5
    },
    {
      "key": "B2,D2,D3,D4,G2",
      "time": 15.5
    },
    {
      "key": "A2,A2,A3,C4,E3,E4",
      "time": 16.5
    },
    {
      "key": "A3,C4,E3,E4",
      "time": 17.5
    },
    {
      "key": "A2,C3,E2",
      "time": 18.0
    },
    {
      "key": "C3,C4",
      "time": 18.5
    },
    {
      "key": "D3,D4",
      "time": 19.0
    },
    {
      "key": "A2,C3,E2,E3,E4",
      "time": 19.5
    },
    {
      "key": "F3,F4",
      "time": 20.0
    },
    {
      "key": "B3,E2,E2,E3,E4,G3",
      "time": 20.5
    },
    {
      "key": "D3,D4",
      "time": 21.5
    },
    {
      "key": "B2,E2,G2",
      "time": 22.0
    },
    {
      "key": "C3,C4",
      "time": 22.5
    },
    {
      "key": "B2,B2,B3,E2,G2",
      "time": 23.5
    },
    {
      "key": "F2,F2",
      "time": 24.5
    },
    {
      "key": "A2,A3",
      "time": 25.5
    },
    {
      "key": "A2,C3,F3",
      "time": 26.0
    },
    {
      "key": "C3,C4",
      "time": 26.5
    },
    {
      "key": "A2,A3,A4,C3,F3",
      "time": 27.5
    },
    {
      "key": "C4,E2,E2,E4,G3,G4",
      "time": 28.5
    },
    {
      "key": "C4,E4,G3,G4",
      "time": 29.5
    },
    {
      "key": "B2,C3,C4,E2,G2",
      "time": 30.0
    },
    {
      "key": "B2,D3,D4,E2,G2",
      "time": 31.5
    },
    {
      "key": "E3,E4",
      "time": 32.0
    },
    {
      "key": "A#3,D2,D2,D4,F3,F4",
      "time": 32.5
    },
    {
      "key": "E3,E4",
      "time": 33.5
    },
    {
      "key": "A2,D3,F2",
      "time": 34.0
    },
    {
      "key": "D3,D4",
      "time": 34.5
    },
    {
      "key": "A2,C3,C4,D3,F2",
      "time": 35.5
    },
    {
      "key": "B3,D3,D4,G2,G2,G3",
      "time": 36.5
    },
    {
      "key": "B2,D3,G2",
      "time": 38.0
    },
    {
      "key": "C3,C4",
      "time": 38.5
    },
    {
      "key": "B2,B2,B3,D3,G2",
      "time": 39.5
    },
    {
      "key": "C3,C4,G#2,G#2",
      "time": 40.5
    },
    {
      "key": "G#3",
      "time": 41.0
    },
    {
      "key": "G3",
      "time": 41.5
    },
    {
      "key": "C3,D#2,F3,G#2",
      "time": 42.0
    },
    {
      "key": "D#3",
      "time": 43.0
    },
    {
      "key": "C3,D#2,D3,G#2",
      "time": 43.5
    },
    {
      "key": "D#3",
      "time": 44.0
    },
    {
      "key": "A#2,A#2,D4",
      "time": 44.5
    },
    {
      "key": "A#4",
      "time": 45.0
    },
    {
      "key": "G#4",
      "time": 45.5
    },
    {
      "key": "A#2,D2,F2,G4",
      "time": 46.0
    },
    {
      "key": "F4",
      "time": 47.0
    },
    {
      "key": "A#2,D#4,D2,F2",
      "time": 47.5
    },
    {
      "key": "F4",
      "time": 48.0
    },
    {
      "key": "C3,C4,E2,E4,G3",
      "time": 48.5
    },
    {
      "key": "C4",
      "time": 49.5
    },
    {
      "key": "C5",
      "time": 50.0
    },
    {
      "key": "B3",
      "time": 50.5
    },
    {
      "key": "B4",
      "time": 51.0
    },
    {
      "key": "A3",
      "time": 51.5
    },
    {
      "key": "A4",
      "time": 52.0
    },
    {
      "key": "G3",
      "time": 52.5
    },
    {
      "key": "G4",
      "time": 53.0
    },
    {
      "key": "F3",
      "time": 53.5
    },
    {
      "key": "F4",
      "time": 54.0
    },
    {
      "key": "E3",
      "time": 54.5
    },
    {
      "key": "E4",
      "time": 55.0
    },
    {
      "key": "D3",
      "time": 55.5
    },
    {
      "key": "D4",
      "time": 56.0
    },
    {
      "key": "C3,C4,F2,F2",
      "time": 56.5
    },
    {
      "key": "C3,C4,F3,G#2",
      "time": 58.0
    },
    {
      "key": "C4",
      "time": 59.0
    },
    {
      "key": "C3,C4,F3,G#2",
      "time": 59.5
    },
    {
      "key": "C4",
      "time": 60.0
    },
    {
      "key": "A#2,A#2,C4",
      "time": 60.5
    },
    {
      "key": "A#3",
      "time": 61.5
    },
    {
      "key": "A#2,D3,F3,G#3",
      "time": 62.0
    },
    {
      "key": "A#3",
      "time": 63.0
    },
    {
      "key": "A#2,C4,D3,F3",
      "time": 63.5
    },
    {
      "key": "A#3,D3,F3,G2,G2",
      "time": 64.5
    },
    {
      "key": "A#2,D3,G2,G3",
      "time": 66.0
    },
    {
      "key": "A#3",
      "time": 66.5
    },
    {
      "key": "A#3",
      "time": 67.0
    },
    {
      "key": "A#2,A#3,D3,G2",
      "time": 67.5
    },
    {
      "key": "A#3",
      "time": 68.0
    },
    {
      "key": "A#3,C2,C2,D#3,G3",
      "time": 68.5
    },
    {
      "key": "G#3",
      "time": 69.5
    },
    {
      "key": "C3,D#2,G2,G3",
      "time": 70.0
    },
    {
      "key": "G#3",
      "time": 71.0
    },
    {
      "key": "A#3,C3,D#2,G2",
      "time": 71.5
    },
    {
      "key": "C3,D#3,F2,F2,G#3",
      "time": 72.5
    },
    {
      "key": "C3,C3,F2,G#2",
      "time": 74.0
    },
    {
      "key": "G#3",
      "time": 74.5
    },
    {
      "key": "G#3",
      "time": 75.0
    },
    {
      "key": "C3,F2,G#2,G#3",
      "time": 75.5
    },
    {
      "key": "G#3",
      "time": 76.0
    },
    {
      "key": "D2,D2,F3,G#3",
      "time": 76.5
    },
    {
      "key": "G#3",
      "time": 77.5
    },
    {
      "key": "D3,F2,G#2,G3",
      "time": 78.0
    },
    {
      "key": "F3",
      "time": 79.0
    },
    {
      "key": "D3,F2,F3,G#2",
      "time": 79.5
    },
    {
      "key": "F3",
      "time": 80.0
    },
    {
      "key": "C2,C2,C3,F3,G#2",
      "time": 80.5
    },
    {
      "key": "G3",
      "time": 81.5
    },
    {
      "key": "C3,D#2,G2",
      "time": 82.0
    },
    {
      "key": "D#3",
      "time": 82.5
    },
    {
      "key": "F3",
      "time": 83.0
    },
    {
      "key": "C3,D#2,G2",
      "time": 83.5
    },
    {
      "key": "A#2,D3,G3",
      "time": 84.0
    },
    {
      "key": "D#2,D#2",
      "time": 84.5
    },
    {
      "key": "A#2,D#3,G2",
      "time": 86.0
    },
    {
      "key": "G#3",
      "time": 87.0
    },
    {
      "key": "A#2,D#3,G#3,G2",
      "time": 87.5
    },
    {
      "key": "A#3",
      "time": 88.0
    },
    {
      "key": "C4,D#3,G#2,G#2,G3",
      "time": 88.5
    },
    {
      "key": "C3,C4,D#3,G#2",
      "time": 90.0
    },
    {
      "key": "C4",
      "time": 91.0
    },
    {
      "key": "C3,D#3,G#2",
      "time": 91.5
    },
    {
      "key": "C4",
      "time": 92.0
    },
    {
      "key": "C4,D#3,G#2,G#2,G3",
      "time": 92.5
    },
    {
      "key": "A#3",
      "time": 93.5
    },
    {
      "key": "C3,D#3,G#2,G#3",
      "time": 94.0
    },
    {
      "key": "A#3",
      "time": 95.0
    },
    {
      "key": "C3,C4,D#3,G#2",
      "time": 95.5
    },
    {
      "key": "A#3,D3,F3,G2,G2",
      "time": 96.5
    },
    {
      "key": "A#2,D3,G#3,G2",
      "time": 98.0
    },
    {
      "key": "A#3",
      "time": 98.5
    },
    {
      "key": "C4",
      "time": 99.0
    },
    {
      "key": "A#2,D3,G2",
      "time": 99.5
    },
    {
      "key": "D4",
      "time": 100.0
    },
    {
      "key": "A#3,C2,C2,D4,G3",
      "time": 100.5
    },
    {
      "key": "D#4",
      "time": 101.5
    },
    {
      "key": "C3,D#2,G2",
      "time": 102.0
    },
    {
      "key": "A#3",
      "time": 102.5
    },
    {
      "key": "G#3",
      "time": 103.0
    },
    {
      "key": "C3,D#2,G2",
      "time": 103.5
    },
    {
      "key": "G3",
      "time": 104.0
    },
    {
      "key": "C3,D#3,F2,F2,G#3",
      "time": 104.5
    },
    {
      "key": "C3,F2,G#2",
      "time": 106.0
    },
    {
      "key": "A#3",
      "time": 107.0
    },
    {
      "key": "C3,F2,G#2",
      "time": 107.5
    },
    {
      "key": "G#3",
      "time": 108.0
    },
    {
      "key": "B2,D3,G2,G2,G3",
      "time": 108.5
    },
    {
      "key": "B2,D3,D3,G2,G3",
      "time": 110.0
    },
    {
      "key": "D3,G3",
      "time": 110.5
    },
    {
      "key": "D#4,G4",
      "time": 111.0
    },
    {
      "key": "B2,D3,G2",
      "time": 111.5
    },
    {
      "key": "C4,F4",
      "time": 112.0
    },
    {
      "key": "C2,C2,C4,F4,G#3",
      "time": 112.5
    },
    {
      "key": "C3,D#2,G2",
      "time": 114.0
    },
    {
      "key": "F4",
      "time": 114.5
    },
    {
      "key": "D#4",
      "time": 115.0
    },
    {
      "key": "C3,D#2,D4,G2",
      "time": 115.5
    },
    {
      "key": "D#4",
      "time": 116.0
    },
    {
      "key": "A#2,A#2",
      "time": 116.5
    },
    {
      "key": "A#2,C4,D3,F3",
      "time": 118.0
    },
    {
      "key": "C4",
      "time": 118.5
    },
    {
      "key": "A#2,D3,D4,F3",
      "time": 119.5
    },
    {
      "key": "C4,D#4,G#2,G#2,G#3",
      "time": 120.5
    },
    {
      "key": "D#4",
      "time": 121.0
    },
    {
      "key": "C3,C4,D#3,G#2",
      "time": 122.0
    },
    {
      "key": "D#4",
      "time": 122.5
    },
    {
      "key": "C3,D#3,G#2",
      "time": 123.5
    },
    {
      "key": "C4",
      "time": 124.0
    },
    {
      "key": "C4,D#4,G#2,G#2,G#3",
      "time": 124.5
    },
    {
      "key": "C3,D#3,D#4,G#2",
      "time": 126.0
    },
    {
      "key": "F4",
      "time": 126.5
    },
    {
      "key": "D#4",
      "time": 127.0
    },
    {
      "key": "C3,D#3,D4,G#2",
      "time": 127.5
    },
    {
      "key": "C4",
      "time": 128.0
    },
    {
      "key": "C4,D#3,G2,G2,G3",
      "time": 128.5
    },
    {
      "key": "A#3",
      "time": 129.0
    },
    {
      "key": "A#2,D3,G2,G3",
      "time": 130.0
    },
    {
      "key": "A#3",
      "time": 130.5
    },
    {
      "key": "A#3",
      "time": 131.0
    },
    {
      "key": "A#2,D3,G2",
      "time": 131.5
    },
    {
      "key": "G3",
      "time": 132.0
    },
    {
      "key": "A#3,D#3,G2,G2,G3",
      "time": 132.5
    },
    {
      "key": "A#2,D3,G2,G3",
      "time": 134.0
    },
    {
      "key": "A#3",
      "time": 134.5
    },
    {
      "key": "C4",
      "time": 135.0
    },
    {
      "key": "A#2,D3,G2",
      "time": 135.5
    },
    {
      "key": "D4",
      "time": 136.0
    },
    {
      "key": "A#3,C2,C2,D#4,G3",
      "time": 136.5
    },
    {
      "key": "D4",
      "time": 137.0
    },
    {
      "key": "C3,D#2,D#4,G2",
      "time": 138.0
    },
    {
      "key": "C4",
      "time": 138.5
    },
    {
      "key": "C3,D#2,G2",
      "time": 139.5
    },
    {
      "key": "C4,D#4,F2,F2,G#3",
      "time": 140.5
    },
    {
      "key": "D4",
      "time": 141.0
    },
    {
      "key": "A2,C3,D#4,F2",
      "time": 142.0
    },
    {
      "key": "C4",
      "time": 142.5
    },
    {
      "key": "A2,C3,F2,G4",
      "time": 143.5
    },
    {
      "key": "A#2,A#2,A#3,D4,F4",
      "time": 144.5
    },
    {
      "key": "A#2,D3,F3,F4",
      "time": 146.0
    },
    {
      "key": "F4",
      "time": 146.5
    },
    {
      "key": "D#4",
      "time": 147.0
    },
    {
      "key": "A#2,D3,F3,F4",
      "time": 147.5
    },
    {
      "key": "A#3,D4,G4",
      "time": 148.0
    },
    {
      "key": "G3,G4",
      "time": 149.0
    },
    {
      "key": "F3,F4",
      "time": 149.5
    },
    {
      "key": "G3,G4",
      "time": 150.0
    },
    {
      "key": "E3,E4",
      "time": 150.5
    },
    {
      "key": "G3,G4",
      "time": 151.0
    },
    {
      "key": "D3,D4",
      "time": 151.5
    },
    {
      "key": "G3,G4",
      "time": 152.0
    },
    {
      "key": "C2,C2,C4,E4,G3,G4",
      "time": 152.5
    },
    {
      "key": "C4,E4,G3,G4",
      "time": 153.5
    },
    {
      "key": "C3,E2,G2",
      "time": 154.0
    },
    {
      "key": "E3,E4",
      "time": 154.5
    },
    {
      "key": "F3,F4",
      "time": 155.0
    },
    {
      "key": "C3,E2,G2,G3,G4",
      "time": 155.5
    },
    {
      "key": "A3,A4",
      "time": 156.0
    },
    {
      "key": "B3,D4,G2,G2,G3,G4",
      "time": 156.5
    },
    {
      "key": "F3,F4",
      "time": 157.5
    },
    {
      "key": "B2,D2,G2",
      "time": 158.0
    },
    {
      "key": "E3,E4",
      "time": 158.5
    },
    {
      "key": "B2,D2,D3,D4,G2",
      "time": 159.5
    },
    {
      "key": "A2,A2,A3,C4,E3,E4",
      "time": 160.5
    },
    {
      "key": "A3,C4,E3,E4",
      "time": 161.5
    },
    {
      "key": "A2,C3,E2",
      "time": 162.0
    },
    {
      "key": "C3,C4",
      "time": 162.5
    },
    {
      "key": "D3,D4",
      "time": 163.0
    },
    {
      "key": "A2,C3,E2,E3,E4",
      "time": 163.5
    },
    {
      "key": "F3,F4",
      "time": 164.0
    },
    {
      "key": "B3,E2,E2,E3,E4,G3",
      "time": 164.5
    },
    {
      "key": "D3,D4",
      "time": 165.5
    },
    {
      "key": "B2,E2,G2",
      "time": 166.0
    },
    {
      "key": "C3,C4",
      "time": 166.5
    },
    {
      "key": "B2,B2,B3,E2,G2",
      "time": 167.5
    },
    {
      "key": "F2,F2",
      "time": 168.5
    },
    {
      "key": "A2,A3",
      "time": 169.5
    },
    {
      "key": "A2,C3,F2",
      "time": 170.0
    },
    {
      "key": "C3,C4",
      "time": 170.5
    },
    {
      "key": "A2,A3,A4,C3,F2",
      "time": 171.5
    },
    {
      "key": "C4,E2,E2,E4,G3,G4",
      "time": 172.5
    },
    {
      "key": "C4,E4,G3,G4",
      "time": 173.5
    },
    {
      "key": "B2,C3,C4,E2,G2",
      "time": 174.0
    },
    {
      "key": "B2,D3,D4,E2,G2",
      "time": 175.5
    },
    {
      "key": "E3,E4",
      "time": 176.0
    },
    {
      "key": "A#3,D2,D2,D4,F3,F4",
      "time": 176.5
    },
    {
      "key": "E3,E4",
      "time": 177.5
    },
    {
      "key": "A2,D3,F2",
      "time": 178.0
    },
    {
      "key": "D3,D4",
      "time": 178.5
    },
    {
      "key": "A2,C3,C4,D3,F2",
      "time": 179.5
    },
    {
      "key": "B3,E2,E2,E3,E4,G3",
      "time": 180.5
    },
    {
      "key": "B2,E2,F3,F4,G#2",
      "time": 182.0
    },
    {
      "key": "E3,E4",
      "time": 182.25
    },
    {
      "key": "D3,D4",
      "time": 182.5
    },
    {
      "key": "B2,E2,G#2",
      "time": 183.5
    },
    {
      "key": "C2,C2,C4,E4,G3,G4",
      "time": 184.5
    },
    {
      "key": "C4,E4,G3,G4",
      "time": 185.5
    },
    {
      "key": "C3,E2,G2",
      "time": 186.0
    },
    {
      "key": "E3,E4",
      "time": 186.5
    },
    {
      "key": "F3,F4",
      "time": 187.0
    },
    {
      "key": "C3,E2,G2,G3,G4",
      "time": 187.5
    },
    {
      "key": "A3,A4",
      "time": 188.0
    },
    {
      "key": "B3,D4,G2,G2,G3,G4",
      "time": 188.5
    },
    {
      "key": "F3,F4",
      "time": 189.5
    },
    {
      "key": "B2,D2,G2",
      "time": 190.0
    },
    {
      "key": "E3,E4",
      "time": 190.5
    },
    {
      "key": "B2,D2,D3,D4,G2",
      "time": 191.5
    },
    {
      "key": "A2,A2,A3,C4,E3,E4",
      "time": 192.5
    },
    {
      "key": "A3,C4,E3,E4",
      "time": 193.5
    },
    {
      "key": "A2,C3,E2",
      "time": 194.0
    },
    {
      "key": "C3,C4",
      "time": 194.5
    },
    {
      "key": "D3,D4",
      "time": 195.0
    },
    {
      "key": "A2,C3,E2,E3,E4",
      "time": 195.5
    },
    {
      "key": "F3,F4",
      "time": 196.0
    },
    {
      "key": "B3,E2,E2,E3,E4,G3",
      "time": 196.5
    },
    {
      "key": "D3,D4",
      "time": 197.5
    },
    {
      "key": "B2,E2,G2",
      "time": 198.0
    },
    {
      "key": "C3,C4",
      "time": 198.5
    },
    {
      "key": "B2,B2,B3,E2,G2",
      "time": 199.5
    },
    {
      "key": "F2,F2",
      "time": 200.5
    },
    {
      "key": "A2,A3",
      "time": 201.5
    },
    {
      "key": "A2,C3,F2",
      "time": 202.0
    },
    {
      "key": "C3,C4",
      "time": 202.5
    },
    {
      "key": "A2,A3,A4,C3,F2",
      "time": 203.5
    },
    {
      "key": "C4,E2,E2,E4,G3,G4",
      "time": 204.5
    },
    {
      "key": "C4,E4,G3,G4",
      "time": 205.5
    },
    {
      "key": "B2,C3,C4,E2,G2",
      "time": 206.0
    },
    {
      "key": "B2,D3,D4,E2,G2",
      "time": 207.5
    },
    {
      "key": "E3,E4",
      "time": 208.0
    },
    {
      "key": "A#3,D2,D2,D4,F3,F4",
      "time": 208.5
    },
    {
      "key": "E3,E4",
      "time": 209.5
    },
    {
      "key": "A2,D3,F2",
      "time": 210.0
    },
    {
      "key": "D3,D4",
      "time": 210.5
    },
    {
      "key": "A2,C3,C4,D3,F2",
      "time": 211.5
    },
    {
      "key": "D3,G2,G2",
      "time": 212.5
    },
    {
      "key": "G3",
      "time": 212.632
    },
    {
      "key": "B3",
      "time": 212.764
    },
    {
      "key": "D4",
      "time": 212.9
    },
    {
      "key": "B2,D3,G3",
      "time": 214.0
    },
    {
      "key": "C3,C4",
      "time": 214.5
    },
    {
      "key": "B2,B2,B3,D3,G3",
      "time": 215.5
    },
    {
      "key": "C3,C4,G#2,G#2",
      "time": 216.5
    },
    {
      "key": "G#3",
      "time": 217.0
    },
    {
      "key": "G3",
      "time": 217.5
    },
    {
      "key": "C3,D#2,F3,G#2",
      "time": 218.0
    },
    {
      "key": "D#3",
      "time": 219.0
    },
    {
      "key": "C3,D#2,D3,G#2",
      "time": 219.5
    },
    {
      "key": "D#3",
      "time": 220.0
    },
    {
      "key": "A#2,A#2,D4",
      "time": 220.5
    },
    {
      "key": "A#4",
      "time": 221.0
    },
    {
      "key": "G#4",
      "time": 221.5
    },
    {
      "key": "A#2,D2,F2,G4",
      "time": 222.0
    },
    {
      "key": "F4",
      "time": 223.0
    },
    {
      "key": "A#2,D#4,D2,F2",
      "time": 223.5
    },
    {
      "key": "F4",
      "time": 224.0
    },
    {
      "key": "C2,G3",
      "time": 224.5
    },
    {
      "key": "C4,F2",
      "time": 224.632
    },
    {
      "key": "F4,G2",
      "time": 224.764
    },
    {
      "key": "F3,F4",
      "time": 226.5
    },
    {
      "key": "G3,G4",
      "time": 227.0
    },
    {
      "key": "F3,F4",
      "time": 227.5
    },
    {
      "key": "E3,E4",
      "time": 228.0
    }
  ]
}